{
  "meta": {
    "start_time": "2026-04-07T20:23:21.712914",
    "end_time": "N/A",
    "duration_hours": 1,
    "testnet": true
  },
  "trades": [
    {
      "time": "2026-04-07T20:23:28.999631",
      "strategy": "volatility",
      "symbol": "ZECUSDT",
      "signal": "BUY",
      "leverage": 20.0,
      "stop_loss": 0.017526,
      "take_profit": 0.026289,
      "entry_price": 0.0,
      "qty": "0.000",
      "pnl_pct": 0.0
    },
    {
      "time": "2026-04-07T20:23:32.447004",
      "strategy": "trend_following",
      "symbol": "ONTUSDT",
      "signal": "SELL",
      "leverage": 17.6,
      "stop_loss": 0.022684,
      "take_profit": 0.034026,
      "entry_price": 0.0,
      "qty": "0.0",
      "pnl_pct": 0.0
    },
    {
      "time": "2026-04-07T20:23:44.340749",
      "strategy": "volatility",
      "symbol": "ZECUSDT",
      "signal": "BUY",
      "leverage": 20.0,
      "stop_loss": 0.017526,
      "take_profit": 0.026289,
      "entry_price": 0.0,
      "qty": "0.000",
      "pnl_pct": 0.0
    },
    {
      "time": "2026-04-07T20:23:46.350970",
      "strategy": "trend_following",
      "symbol": "ONTUSDT",
      "signal": "SELL",
      "leverage": 17.6,
      "stop_loss": 0.022684,
      "take_profit": 0.034026,
      "entry_price": 0.0,
      "qty": "0.0",
      "pnl_pct": 0.0
    },
    {
      "time": "2026-04-07T20:23:58.711954",
      "strategy": "volatility",
      "symbol": "ZECUSDT",
      "signal": "BUY",
      "leverage": 20.0,
      "stop_loss": 0.017526,
      "take_profit": 0.026289,
      "entry_price": 0.0,
      "qty": "0.000",
      "pnl_pct": 0.0
    },
    {
      "time": "2026-04-07T20:24:00.815383",
      "strategy": "trend_following",
      "symbol": "ONTUSDT",
      "signal": "SELL",
      "leverage": 17.6,
      "stop_loss": 0.022684,
      "take_profit": 0.034026,
      "entry_price": 0.0,
      "qty": "0.0",
      "pnl_pct": 0.0
    },
    {
      "time": "2026-04-07T20:24:12.763497",
      "strategy": "volatility",
      "symbol": "ZECUSDT",
      "signal": "BUY",
      "leverage": 20.0,
      "stop_loss": 0.017526,
      "take_profit": 0.026289,
      "entry_price": 0.0,
      "qty": "0.000",
      "pnl_pct": 0.0
    },
    {
      "time": "2026-04-07T20:24:14.519212",
      "strategy": "trend_following",
      "symbol": "ONTUSDT",
      "signal": "SELL",
      "leverage": 17.6,
      "stop_loss": 0.022684,
      "take_profit": 0.034026,
      "entry_price": 0.0,
      "qty": "0.0",
      "pnl_pct": 0.0
    },
    {
      "time": "2026-04-07T20:24:26.877072",
      "strategy": "volatility",
      "symbol": "ZECUSDT",
      "signal": "BUY",
      "leverage": 20.0,
      "stop_loss": 0.017526,
      "take_profit": 0.026289,
      "entry_price": 0.0,
      "qty": "0.000",
      "pnl_pct": 0.0
    },
    {
      "time": "2026-04-07T20:24:28.914472",
      "strategy": "trend_following",
      "symbol": "ONTUSDT",
      "signal": "SELL",
      "leverage": 17.6,
      "stop_loss": 0.022684,
      "take_profit": 0.034026,
      "entry_price": 0.0,
      "qty": "0.0",
      "pnl_pct": 0.0
    },
    {
      "time": "2026-04-07T20:24:40.726556",
      "strategy": "volatility",
      "symbol": "ZECUSDT",
      "signal": "BUY",
      "leverage": 20.0,
      "stop_loss": 0.017526,
      "take_profit": 0.026289,
      "entry_price": 0.0,
      "qty": "0.000",
      "pnl_pct": 0.0
    },
    {
      "time": "2026-04-07T20:24:42.770661",
      "strategy": "trend_following",
      "symbol": "ONTUSDT",
      "signal": "SELL",
      "leverage": 17.6,
      "stop_loss": 0.022684,
      "take_profit": 0.034026,
      "entry_price": 0.0,
      "qty": "0.0",
      "pnl_pct": 0.0
    },
    {
      "time": "2026-04-07T20:24:54.532796",
      "strategy": "volatility",
      "symbol": "ZECUSDT",
      "signal": "BUY",
      "leverage": 20.0,
      "stop_loss": 0.017526,
      "take_profit": 0.026289,
      "entry_price": 0.0,
      "qty": "0.000",
      "pnl_pct": 0.0
    },
    {
      "time": "2026-04-07T20:24:56.342014",
      "strategy": "trend_following",
      "symbol": "ONTUSDT",
      "signal": "SELL",
      "leverage": 17.6,
      "stop_loss": 0.022684,
      "take_profit": 0.034026,
      "entry_price": 0.0,
      "qty": "0.0",
      "pnl_pct": 0.0
    },
    {
      "time": "2026-04-07T20:25:08.363243",
      "strategy": "volatility",
      "symbol": "ZECUSDT",
      "signal": "BUY",
      "leverage": 20.0,
      "stop_loss": 0.017526,
      "take_profit": 0.026289,
      "entry_price": 0.0,
      "qty": "0.000",
      "pnl_pct": 0.0
    },
    {
      "time": "2026-04-07T20:25:10.323417",
      "strategy": "trend_following",
      "symbol": "ONTUSDT",
      "signal": "SELL",
      "leverage": 17.6,
      "stop_loss": 0.022684,
      "take_profit": 0.034026,
      "entry_price": 0.0,
      "qty": "0.0",
      "pnl_pct": 0.0
    },
    {
      "time": "2026-04-07T20:25:22.192888",
      "strategy": "volatility",
      "symbol": "ZECUSDT",
      "signal": "BUY",
      "leverage": 20.0,
      "stop_loss": 0.017526,
      "take_profit": 0.026289,
      "entry_price": 0.0,
      "qty": "0.000",
      "pnl_pct": 0.0
    },
    {
      "time": "2026-04-07T20:25:24.004930",
      "strategy": "trend_following",
      "symbol": "ONTUSDT",
      "signal": "SELL",
      "leverage": 17.6,
      "stop_loss": 0.022684,
      "take_profit": 0.034026,
      "entry_price": 0.0,
      "qty": "0.0",
      "pnl_pct": 0.0
    },
    {
      "time": "2026-04-07T20:25:36.165704",
      "strategy": "volatility",
      "symbol": "ZECUSDT",
      "signal": "BUY",
      "leverage": 20.0,
      "stop_loss": 0.017526,
      "take_profit": 0.026289,
      "entry_price": 0.0,
      "qty": "0.000",
      "pnl_pct": 0.0
    },
    {
      "time": "2026-04-07T20:25:38.041116",
      "strategy": "trend_following",
      "symbol": "ONTUSDT",
      "signal": "SELL",
      "leverage": 17.6,
      "stop_loss": 0.022684,
      "take_profit": 0.034026,
      "entry_price": 0.0,
      "qty": "0.0",
      "pnl_pct": 0.0
    },
    {
      "time": "2026-04-07T20:25:50.170307",
      "strategy": "volatility",
      "symbol": "ZECUSDT",
      "signal": "BUY",
      "leverage": 20.0,
      "stop_loss": 0.017526,
      "take_profit": 0.026289,
      "entry_price": 0.0,
      "qty": "0.000",
      "pnl_pct": 0.0
    },
    {
      "time": "2026-04-07T20:25:51.954853",
      "strategy": "trend_following",
      "symbol": "ONTUSDT",
      "signal": "SELL",
      "leverage": 17.6,
      "stop_loss": 0.022684,
      "take_profit": 0.034026,
      "entry_price": 0.0,
      "qty": "0.0",
      "pnl_pct": 0.0
    },
    {
      "time": "2026-04-07T20:26:03.793621",
      "strategy": "volatility",
      "symbol": "ZECUSDT",
      "signal": "BUY",
      "leverage": 20.0,
      "stop_loss": 0.017526,
      "take_profit": 0.026289,
      "entry_price": 0.0,
      "qty": "0.000",
      "pnl_pct": 0.0
    },
    {
      "time": "2026-04-07T20:26:05.644210",
      "strategy": "trend_following",
      "symbol": "ONTUSDT",
      "signal": "SELL",
      "leverage": 17.6,
      "stop_loss": 0.022684,
      "take_profit": 0.034026,
      "entry_price": 0.0,
      "qty": "0.0",
      "pnl_pct": 0.0
    },
    {
      "time": "2026-04-07T20:26:17.890203",
      "strategy": "volatility",
      "symbol": "ZECUSDT",
      "signal": "BUY",
      "leverage": 20.0,
      "stop_loss": 0.017526,
      "take_profit": 0.026289,
      "entry_price": 0.0,
      "qty": "0.000",
      "pnl_pct": 0.0
    },
    {
      "time": "2026-04-07T20:26:19.842646",
      "strategy": "trend_following",
      "symbol": "ONTUSDT",
      "signal": "SELL",
      "leverage": 17.6,
      "stop_loss": 0.022684,
      "take_profit": 0.034026,
      "entry_price": 0.0,
      "qty": "0.0",
      "pnl_pct": 0.0
    },
    {
      "time": "2026-04-07T20:26:31.808533",
      "strategy": "volatility",
      "symbol": "ZECUSDT",
      "signal": "BUY",
      "leverage": 20.0,
      "stop_loss": 0.017526,
      "take_profit": 0.026289,
      "entry_price": 0.0,
      "qty": "0.000",
      "pnl_pct": 0.0
    },
    {
      "time": "2026-04-07T20:26:33.759821",
      "strategy": "trend_following",
      "symbol": "ONTUSDT",
      "signal": "SELL",
      "leverage": 17.6,
      "stop_loss": 0.022684,
      "take_profit": 0.034026,
      "entry_price": 0.0,
      "qty": "0.0",
      "pnl_pct": 0.0
    },
    {
      "time": "2026-04-07T20:26:46.094547",
      "strategy": "volatility",
      "symbol": "ZECUSDT",
      "signal": "BUY",
      "leverage": 20.0,
      "stop_loss": 0.017526,
      "take_profit": 0.026289,
      "entry_price": 0.0,
      "qty": "0.000",
      "pnl_pct": 0.0
    },
    {
      "time": "2026-04-07T20:26:48.496846",
      "strategy": "trend_following",
      "symbol": "ONTUSDT",
      "signal": "SELL",
      "leverage": 17.6,
      "stop_loss": 0.022684,
      "take_profit": 0.034026,
      "entry_price": 0.0,
      "qty": "0.0",
      "pnl_pct": 0.0
    },
    {
      "time": "2026-04-07T20:27:00.381313",
      "strategy": "volatility",
      "symbol": "ZECUSDT",
      "signal": "BUY",
      "leverage": 20.0,
      "stop_loss": 0.017526,
      "take_profit": 0.026289,
      "entry_price": 0.0,
      "qty": "0.000",
      "pnl_pct": 0.0
    },
    {
      "time": "2026-04-07T20:27:02.133860",
      "strategy": "trend_following",
      "symbol": "ONTUSDT",
      "signal": "SELL",
      "leverage": 17.6,
      "stop_loss": 0.022684,
      "take_profit": 0.034026,
      "entry_price": 0.0,
      "qty": "0.0",
      "pnl_pct": 0.0
    },
    {
      "time": "2026-04-07T20:27:14.093504",
      "strategy": "volatility",
      "symbol": "ZECUSDT",
      "signal": "BUY",
      "leverage": 20.0,
      "stop_loss": 0.017526,
      "take_profit": 0.026289,
      "entry_price": 0.0,
      "qty": "0.000",
      "pnl_pct": 0.0
    },
    {
      "time": "2026-04-07T20:27:15.896377",
      "strategy": "trend_following",
      "symbol": "ONTUSDT",
      "signal": "SELL",
      "leverage": 17.6,
      "stop_loss": 0.022684,
      "take_profit": 0.034026,
      "entry_price": 0.0,
      "qty": "0.0",
      "pnl_pct": 0.0
    },
    {
      "time": "2026-04-07T20:27:28.104254",
      "strategy": "volatility",
      "symbol": "ZECUSDT",
      "signal": "BUY",
      "leverage": 20.0,
      "stop_loss": 0.017526,
      "take_profit": 0.026289,
      "entry_price": 0.0,
      "qty": "0.000",
      "pnl_pct": 0.0
    },
    {
      "time": "2026-04-07T20:27:29.943634",
      "strategy": "trend_following",
      "symbol": "ONTUSDT",
      "signal": "SELL",
      "leverage": 17.6,
      "stop_loss": 0.022684,
      "take_profit": 0.034026,
      "entry_price": 0.0,
      "qty": "0.0",
      "pnl_pct": 0.0
    },
    {
      "time": "2026-04-07T20:27:41.803644",
      "strategy": "volatility",
      "symbol": "ZECUSDT",
      "signal": "BUY",
      "leverage": 20.0,
      "stop_loss": 0.017526,
      "take_profit": 0.026289,
      "entry_price": 0.0,
      "qty": "0.000",
      "pnl_pct": 0.0
    },
    {
      "time": "2026-04-07T20:27:43.566127",
      "strategy": "trend_following",
      "symbol": "ONTUSDT",
      "signal": "SELL",
      "leverage": 17.6,
      "stop_loss": 0.022684,
      "take_profit": 0.034026,
      "entry_price": 0.0,
      "qty": "0.0",
      "pnl_pct": 0.0
    },
    {
      "time": "2026-04-07T20:27:55.789634",
      "strategy": "volatility",
      "symbol": "ZECUSDT",
      "signal": "BUY",
      "leverage": 20.0,
      "stop_loss": 0.017526,
      "take_profit": 0.026289,
      "entry_price": 0.0,
      "qty": "0.000",
      "pnl_pct": 0.0
    },
    {
      "time": "2026-04-07T20:27:57.555417",
      "strategy": "trend_following",
      "symbol": "ONTUSDT",
      "signal": "SELL",
      "leverage": 17.6,
      "stop_loss": 0.022684,
      "take_profit": 0.034026,
      "entry_price": 0.0,
      "qty": "0.0",
      "pnl_pct": 0.0
    },
    {
      "time": "2026-04-07T20:28:09.661731",
      "strategy": "volatility",
      "symbol": "ZECUSDT",
      "signal": "BUY",
      "leverage": 20.0,
      "stop_loss": 0.017526,
      "take_profit": 0.026289,
      "entry_price": 0.0,
      "qty": "0.000",
      "pnl_pct": 0.0
    },
    {
      "time": "2026-04-07T20:28:11.467058",
      "strategy": "trend_following",
      "symbol": "ONTUSDT",
      "signal": "SELL",
      "leverage": 17.6,
      "stop_loss": 0.022684,
      "take_profit": 0.034026,
      "entry_price": 0.0,
      "qty": "0.0",
      "pnl_pct": 0.0
    },
    {
      "time": "2026-04-07T20:28:23.734961",
      "strategy": "volatility",
      "symbol": "ZECUSDT",
      "signal": "BUY",
      "leverage": 20.0,
      "stop_loss": 0.017526,
      "take_profit": 0.026289,
      "entry_price": 0.0,
      "qty": "0.000",
      "pnl_pct": 0.0
    },
    {
      "time": "2026-04-07T20:28:25.952868",
      "strategy": "trend_following",
      "symbol": "ONTUSDT",
      "signal": "SELL",
      "leverage": 17.6,
      "stop_loss": 0.022684,
      "take_profit": 0.034026,
      "entry_price": 0.0,
      "qty": "0.0",
      "pnl_pct": 0.0
    },
    {
      "time": "2026-04-07T20:28:41.991645",
      "strategy": "volatility",
      "symbol": "ZECUSDT",
      "signal": "BUY",
      "leverage": 20.0,
      "stop_loss": 0.017526,
      "take_profit": 0.026289,
      "entry_price": 0.0,
      "qty": "0.000",
      "pnl_pct": 0.0
    },
    {
      "time": "2026-04-07T20:28:45.243284",
      "strategy": "trend_following",
      "symbol": "ONTUSDT",
      "signal": "SELL",
      "leverage": 17.6,
      "stop_loss": 0.022684,
      "take_profit": 0.034026,
      "entry_price": 0.0,
      "qty": "0.0",
      "pnl_pct": 0.0
    },
    {
      "time": "2026-04-07T20:28:57.686674",
      "strategy": "volatility",
      "symbol": "ZECUSDT",
      "signal": "BUY",
      "leverage": 20.0,
      "stop_loss": 0.017526,
      "take_profit": 0.026289,
      "entry_price": 0.0,
      "qty": "0.000",
      "pnl_pct": 0.0
    },
    {
      "time": "2026-04-07T20:28:59.917202",
      "strategy": "trend_following",
      "symbol": "ONTUSDT",
      "signal": "SELL",
      "leverage": 17.6,
      "stop_loss": 0.022684,
      "take_profit": 0.034026,
      "entry_price": 0.0,
      "qty": "0.0",
      "pnl_pct": 0.0
    },
    {
      "time": "2026-04-07T20:29:12.395116",
      "strategy": "volatility",
      "symbol": "ZECUSDT",
      "signal": "BUY",
      "leverage": 20.0,
      "stop_loss": 0.017526,
      "take_profit": 0.026289,
      "entry_price": 0.0,
      "qty": "0.000",
      "pnl_pct": 0.0
    },
    {
      "time": "2026-04-07T20:29:14.446344",
      "strategy": "trend_following",
      "symbol": "ONTUSDT",
      "signal": "SELL",
      "leverage": 17.6,
      "stop_loss": 0.022684,
      "take_profit": 0.034026,
      "entry_price": 0.0,
      "qty": "0.0",
      "pnl_pct": 0.0
    },
    {
      "time": "2026-04-07T20:29:26.471219",
      "strategy": "volatility",
      "symbol": "ZECUSDT",
      "signal": "BUY",
      "leverage": 20.0,
      "stop_loss": 0.017526,
      "take_profit": 0.026289,
      "entry_price": 0.0,
      "qty": "0.000",
      "pnl_pct": 0.0
    },
    {
      "time": "2026-04-07T20:29:28.693335",
      "strategy": "trend_following",
      "symbol": "ONTUSDT",
      "signal": "SELL",
      "leverage": 17.6,
      "stop_loss": 0.022684,
      "take_profit": 0.034026,
      "entry_price": 0.0,
      "qty": "0.0",
      "pnl_pct": 0.0
    },
    {
      "time": "2026-04-07T20:29:40.813127",
      "strategy": "volatility",
      "symbol": "ZECUSDT",
      "signal": "BUY",
      "leverage": 20.0,
      "stop_loss": 0.017526,
      "take_profit": 0.026289,
      "entry_price": 0.0,
      "qty": "0.000",
      "pnl_pct": 0.0
    },
    {
      "time": "2026-04-07T20:29:43.302031",
      "strategy": "trend_following",
      "symbol": "ONTUSDT",
      "signal": "SELL",
      "leverage": 17.6,
      "stop_loss": 0.022684,
      "take_profit": 0.034026,
      "entry_price": 0.0,
      "qty": "0.0",
      "pnl_pct": 0.0
    },
    {
      "time": "2026-04-07T20:29:55.371200",
      "strategy": "volatility",
      "symbol": "ZECUSDT",
      "signal": "BUY",
      "leverage": 20.0,
      "stop_loss": 0.017526,
      "take_profit": 0.026289,
      "entry_price": 0.0,
      "qty": "0.000",
      "pnl_pct": 0.0
    },
    {
      "time": "2026-04-07T20:29:57.534565",
      "strategy": "trend_following",
      "symbol": "ONTUSDT",
      "signal": "SELL",
      "leverage": 17.6,
      "stop_loss": 0.022684,
      "take_profit": 0.034026,
      "entry_price": 0.0,
      "qty": "0.0",
      "pnl_pct": 0.0
    },
    {
      "time": "2026-04-07T20:30:09.849306",
      "strategy": "volatility",
      "symbol": "ZECUSDT",
      "signal": "BUY",
      "leverage": 20.0,
      "stop_loss": 0.017526,
      "take_profit": 0.026289,
      "entry_price": 0.0,
      "qty": "0.000",
      "pnl_pct": 0.0
    },
    {
      "time": "2026-04-07T20:30:22.544012",
      "strategy": "volatility",
      "symbol": "ZECUSDT",
      "signal": "BUY",
      "leverage": 20.0,
      "stop_loss": 0.017526,
      "take_profit": 0.026289,
      "entry_price": 0.0,
      "qty": "0.000",
      "pnl_pct": 0.0
    },
    {
      "time": "2026-04-07T20:30:34.868441",
      "strategy": "volatility",
      "symbol": "ZECUSDT",
      "signal": "BUY",
      "leverage": 20.0,
      "stop_loss": 0.017526,
      "take_profit": 0.026289,
      "entry_price": 0.0,
      "qty": "0.000",
      "pnl_pct": 0.0
    },
    {
      "time": "2026-04-07T20:30:47.307841",
      "strategy": "volatility",
      "symbol": "ZECUSDT",
      "signal": "BUY",
      "leverage": 20.0,
      "stop_loss": 0.017526,
      "take_profit": 0.026289,
      "entry_price": 0.0,
      "qty": "0.000",
      "pnl_pct": 0.0
    },
    {
      "time": "2026-04-07T20:31:00.609537",
      "strategy": "volatility",
      "symbol": "ZECUSDT",
      "signal": "BUY",
      "leverage": 20.0,
      "stop_loss": 0.017526,
      "take_profit": 0.026289,
      "entry_price": 0.0,
      "qty": "0.000",
      "pnl_pct": 0.0
    },
    {
      "time": "2026-04-07T20:31:13.735014",
      "strategy": "volatility",
      "symbol": "ZECUSDT",
      "signal": "BUY",
      "leverage": 20.0,
      "stop_loss": 0.017526,
      "take_profit": 0.026289,
      "entry_price": 0.0,
      "qty": "0.000",
      "pnl_pct": 0.0
    },
    {
      "time": "2026-04-07T20:31:26.486190",
      "strategy": "volatility",
      "symbol": "ZECUSDT",
      "signal": "BUY",
      "leverage": 20.0,
      "stop_loss": 0.017526,
      "take_profit": 0.026289,
      "entry_price": 0.0,
      "qty": "0.000",
      "pnl_pct": 0.0
    }
  ],
  "performance": {
    "momentum": {
      "total_trades": 0,
      "wins": 0,
      "losses": 0,
      "win_rate": 0.0,
      "avg_pnl": 0.0,
      "total_pnl": 0
    },
    "mean_reversion": {
      "total_trades": 0,
      "wins": 0,
      "losses": 0,
      "win_rate": 0.0,
      "avg_pnl": 0.0,
      "total_pnl": 0
    },
    "volatility": {
      "total_trades": 0,
      "wins": 0,
      "losses": 0,
      "win_rate": 0.0,
      "avg_pnl": 0.0,
      "total_pnl": 0
    },
    "trend_following": {
      "total_trades": 0,
      "wins": 0,
      "losses": 0,
      "win_rate": 0.0,
      "avg_pnl": 0.0,
      "total_pnl": 0
    }
  },
  "summary": {
    "end_time": "2026-04-07T20:31:31.225208",
    "total_trades": 63,
    "total_errors": 0,
    "success_rate": 100.0,
    "duration_hours": 1
  }
}